tablediff_arrow/__init__.py
tablediff_arrow/cli.py
tablediff_arrow/compare.py
tablediff_arrow/loader.py
tablediff_arrow/reports.py
tablediff_arrow-0.1.0.dist-info/licenses/LICENSE
tablediff_arrow-0.1.0.dist-info/METADATA
tablediff_arrow-0.1.0.dist-info/WHEEL
tablediff_arrow-0.1.0.dist-info/entry_points.txt
tablediff_arrow-0.1.0.dist-info/top_level.txt
tablediff_arrow-0.1.0.dist-info/RECORD
