Metadata-Version: 2.4
Name: tablediff-arrow
Version: 0.1.0
Summary: Fast, file-based diffs for Parquet/CSV/Arrow (local or S3) with keyed comparisons, per-column tolerances, and HTML/CSV reports—built on Apache Arrow.
Author-email: Prasenjit Singh <psmman@users.noreply.github.com>
License: MIT
Project-URL: Homepage, https://github.com/psmman/tablediff-arrow
Project-URL: Repository, https://github.com/psmman/tablediff-arrow
Project-URL: Issues, https://github.com/psmman/tablediff-arrow/issues
Keywords: diff,parquet,csv,arrow,data-comparison
Classifier: Development Status :: 3 - Alpha
Classifier: Intended Audience :: Developers
Classifier: License :: OSI Approved :: MIT License
Classifier: Programming Language :: Python :: 3
Classifier: Programming Language :: Python :: 3.10
Classifier: Programming Language :: Python :: 3.11
Classifier: Programming Language :: Python :: 3.12
Classifier: Topic :: Software Development :: Libraries :: Python Modules
Requires-Python: >=3.10
License-File: LICENSE
Requires-Dist: pyarrow>=14.0.0
Requires-Dist: pandas>=2.0.0
Requires-Dist: click>=8.0.0
Requires-Dist: jinja2>=3.0.0
Provides-Extra: dev
Requires-Dist: pytest>=7.0.0; extra == "dev"
Requires-Dist: pytest-cov>=4.0.0; extra == "dev"
Requires-Dist: black>=23.0.0; extra == "dev"
Requires-Dist: ruff>=0.1.0; extra == "dev"
Requires-Dist: mypy>=1.0.0; extra == "dev"
Requires-Dist: pre-commit>=3.0.0; extra == "dev"
Provides-Extra: s3
Requires-Dist: s3fs>=2023.0.0; extra == "s3"
Dynamic: license-file
